contextfilter/__init__.py
contextfilter/main.py
contextfilter-0.3.0.dist-info/LICENSE
contextfilter-0.3.0.dist-info/WHEEL
contextfilter-0.3.0.dist-info/METADATA
contextfilter-0.3.0.dist-info/RECORD
