Metadata-Version: 2.1
Name: contextfilter
Version: 0.3.0
Summary: ContextVars Filter for easily enriching log records
Home-page: https://github.com/aviramha/contextfilter
License: MIT
Author: Aviram Hassan
Author-email: aviramyhassan@gmail.com
Requires-Python: >=3.7,<4.0
Classifier: License :: OSI Approved :: MIT License
Classifier: Programming Language :: Python :: 3
Classifier: Programming Language :: Python :: 3.7
Classifier: Programming Language :: Python :: 3.8
Project-URL: Repository, https://github.com/aviramha/contextfilter
